collective_folderprotection/__init__.py
collective_folderprotection/config.py
collective_folderprotection/configure.zcml
collective_folderprotection/events.py
collective_folderprotection/exceptions.py
collective_folderprotection/interfaces.py
collective_folderprotection/overrides.zcml
collective_folderprotection/setuphandlers.py
collective_folderprotection/testing.py
collective_folderprotection/behaviors/__init__.py
collective_folderprotection/behaviors/configure.zcml
collective_folderprotection/behaviors/del_protected.py
collective_folderprotection/behaviors/interfaces.py
collective_folderprotection/behaviors/passwordprotected.py
collective_folderprotection/behaviors/rename_protected.py
collective_folderprotection/browser/__init__.py
collective_folderprotection/browser/alert_viewlet.pt
collective_folderprotection/browser/alert_viewlet.py
collective_folderprotection/browser/configure.zcml
collective_folderprotection/browser/delete_protected.py
collective_folderprotection/browser/passwordprotected.pt
collective_folderprotection/browser/passwordprotected.py
collective_folderprotection/browser/reason_viewlet.pt
collective_folderprotection/browser/reason_viewlet.py
collective_folderprotection/browser/rename_protected.py
collective_folderprotection/browser/widget/__init__.py
collective_folderprotection/browser/widget/configure.zcml
collective_folderprotection/browser/widget/password.py
collective_folderprotection/browser/widget/password_input.pt
collective_folderprotection/profiles/default/actions.xml
collective_folderprotection/profiles/default/browserlayer.xml
collective_folderprotection/profiles/default/metadata.xml
collective_folderprotection/profiles/test_fixture/metadata.xml
collective_folderprotection/profiles/test_fixture/types.xml
collective_folderprotection/profiles/test_fixture/types/folderish_not_protected.xml
collective_folderprotection/profiles/test_fixture/types/folderish_protected.xml
collective_folderprotection/profiles/uninstall/actions.xml
collective_folderprotection-2.4.3.dist-info/METADATA
collective_folderprotection-2.4.3.dist-info/WHEEL
collective_folderprotection-2.4.3.dist-info/entry_points.txt
collective_folderprotection-2.4.3.dist-info/top_level.txt
collective_folderprotection-2.4.3.dist-info/RECORD
