Metadata-Version: 2.1
Name: collective_folderprotection
Version: 2.4.3
Summary: Provide delete, rename and password protection for Plone items.
Home-page: https://github.com/collective/collective_folderprotection
Author: Enfold Systems, Inc.
Author-email: info@enfoldsystems.com
License: gpl
Keywords: folder protection plone
Classifier: Development Status :: 5 - Production/Stable
Classifier: Environment :: Web Environment
Classifier: Framework :: Plone
Classifier: Operating System :: OS Independent
Classifier: Programming Language :: Python
Classifier: Programming Language :: Python :: 3.7
Classifier: Programming Language :: Python :: 3.8
Classifier: Programming Language :: Python :: 3.9
Classifier: Programming Language :: Python :: 3.10
Classifier: Programming Language :: Python :: 3.11
Classifier: Framework :: Plone
Classifier: Framework :: Plone :: 5.2
Classifier: Framework :: Plone :: 6.0
Classifier: Topic :: Software Development :: Libraries :: Python Modules
Requires-Dist: setuptools
Requires-Dist: six
Requires-Dist: plone.app.contenttypes
Provides-Extra: test
Requires-Dist: cssselect ; extra == 'test'
Requires-Dist: lxml ; extra == 'test'
Requires-Dist: mock ; extra == 'test'
Requires-Dist: plone.api >=1.8.5 ; extra == 'test'
Requires-Dist: plone.app.robotframework ; extra == 'test'
Requires-Dist: plone.app.testing[robot] ; extra == 'test'
Requires-Dist: plone.browserlayer ; extra == 'test'
Requires-Dist: plone.cachepurging ; extra == 'test'
Requires-Dist: plone.testing ; extra == 'test'
Requires-Dist: robotsuite ; extra == 'test'
Requires-Dist: testfixtures ; extra == 'test'
Requires-Dist: transaction ; extra == 'test'
Requires-Dist: tzlocal ; extra == 'test'
